rotalabs_verity/__init__.py
rotalabs_verity/_version.py
rotalabs_verity/cli.py
rotalabs_verity/ce2p/__init__.py
rotalabs_verity/ce2p/abducer.py
rotalabs_verity/ce2p/executor.py
rotalabs_verity/ce2p/feedback.py
rotalabs_verity/ce2p/localizer.py
rotalabs_verity/core/__init__.py
rotalabs_verity/core/problem.py
rotalabs_verity/core/python_subset.py
rotalabs_verity/core/types.py
rotalabs_verity/encoder/__init__.py
rotalabs_verity/encoder/parser.py
rotalabs_verity/encoder/symbolic.py
rotalabs_verity/encoder/z3_encoder.py
rotalabs_verity/llm/__init__.py
rotalabs_verity/llm/client.py
rotalabs_verity/llm/prompts.py
rotalabs_verity/problems/__init__.py
rotalabs_verity/problems/registry.py
rotalabs_verity/problems/cb/__init__.py
rotalabs_verity/problems/cb/cb001_circuit_breaker.py
rotalabs_verity/problems/cb/cb002_bulkhead.py
rotalabs_verity/problems/cb/cb003_retry_backoff.py
rotalabs_verity/problems/cb/cb004_timeout_handler.py
rotalabs_verity/problems/cb/cb005_health_check.py
rotalabs_verity/problems/cb/cb006_load_shedder.py
rotalabs_verity/problems/cb/cb007_fallback_handler.py
rotalabs_verity/problems/cb/cb008_graceful_degradation.py
rotalabs_verity/problems/cn/__init__.py
rotalabs_verity/problems/cn/cn001_leader_election.py
rotalabs_verity/problems/cn/cn002_bully_election.py
rotalabs_verity/problems/cn/cn003_ring_election.py
rotalabs_verity/problems/cn/cn004_raft_election.py
rotalabs_verity/problems/cn/cn005_paxos_proposer.py
rotalabs_verity/problems/cn/cn006_paxos_acceptor.py
rotalabs_verity/problems/cn/cn007_view_change.py
rotalabs_verity/problems/cn/cn008_membership.py
rotalabs_verity/problems/cn/cn009_lease_manager.py
rotalabs_verity/problems/co/__init__.py
rotalabs_verity/problems/co/co001_distributed_lock.py
rotalabs_verity/problems/co/co002_semaphore.py
rotalabs_verity/problems/co/co003_rwlock.py
rotalabs_verity/problems/co/co004_barrier.py
rotalabs_verity/problems/co/co005_countdown_latch.py
rotalabs_verity/problems/co/co006_phaser.py
rotalabs_verity-1.0.0.dist-info/METADATA
rotalabs_verity-1.0.0.dist-info/WHEEL
rotalabs_verity-1.0.0.dist-info/entry_points.txt
rotalabs_verity-1.0.0.dist-info/licenses/LICENSE
rotalabs_verity-1.0.0.dist-info/RECORD
