Metadata-Version: 2.4
Name: rotalabs-verity
Version: 1.0.0
Summary: Verity: Neuro-symbolic synthesis of verified code using Z3 and LLMs with CE2P feedback
Project-URL: Homepage, https://rotalabs.ai
Project-URL: Repository, https://github.com/rotalabs/rotalabs-verity
Project-URL: Documentation, https://rotalabs.github.io/rotalabs-verity/
Author-email: Subhadip Mitra <subhadip@rotalabs.ai>, Rotalabs Research <research@rotalabs.ai>
License-Expression: AGPL-3.0-or-later
License-File: LICENSE
Keywords: ce2p,cegis,code-synthesis,formal-methods,llm,neuro-symbolic,smt,verification,z3
Classifier: Development Status :: 4 - Beta
Classifier: Intended Audience :: Developers
Classifier: Intended Audience :: Science/Research
Classifier: License :: OSI Approved :: GNU Affero General Public License v3 or later (AGPLv3+)
Classifier: Programming Language :: Python :: 3
Classifier: Programming Language :: Python :: 3.9
Classifier: Programming Language :: Python :: 3.10
Classifier: Programming Language :: Python :: 3.11
Classifier: Programming Language :: Python :: 3.12
Classifier: Topic :: Scientific/Engineering :: Artificial Intelligence
Classifier: Topic :: Software Development :: Code Generators
Classifier: Topic :: Software Development :: Testing
Requires-Python: >=3.9
Requires-Dist: requests>=2.31.0
Requires-Dist: z3-solver>=4.12.0
Provides-Extra: all
Requires-Dist: anthropic>=0.18.0; extra == 'all'
Requires-Dist: ollama>=0.1.0; extra == 'all'
Requires-Dist: openai>=1.0.0; extra == 'all'
Provides-Extra: anthropic
Requires-Dist: anthropic>=0.18.0; extra == 'anthropic'
Provides-Extra: dev
Requires-Dist: black>=23.0.0; extra == 'dev'
Requires-Dist: mypy>=1.5.0; extra == 'dev'
Requires-Dist: pytest-cov>=4.1.0; extra == 'dev'
Requires-Dist: pytest>=7.4.0; extra == 'dev'
Requires-Dist: ruff>=0.1.0; extra == 'dev'
Provides-Extra: docs
Requires-Dist: mkdocs-material>=9.4.0; extra == 'docs'
Requires-Dist: mkdocs>=1.5.0; extra == 'docs'
Requires-Dist: mkdocstrings[python]>=0.24.0; extra == 'docs'
Provides-Extra: llm
Requires-Dist: anthropic>=0.18.0; extra == 'llm'
Requires-Dist: openai>=1.0.0; extra == 'llm'
Provides-Extra: ollama
Requires-Dist: ollama>=0.1.0; extra == 'ollama'
Provides-Extra: openai
Requires-Dist: openai>=1.0.0; extra == 'openai'
